sourcesense_vessel-1.3.8.data/scripts/vessel-cli
vessel/__init__.py
vessel/cli.py
vessel/logging.py
vessel/pipeline.py
vessel/utilities.py
vessel/version.py
vessel/resources/agent.yaml.jinja2
vessel/resources/alertmanager.yaml.jinja2
vessel/resources/event-engine-ingress.yaml.jinja2
vessel/resources/event-engine.yaml.jinja2
vessel/resources/sentinel.yaml.jinja2
vessel/steps/__init__.py
vessel/steps/deployment.py
vessel/steps/keys.py
vessel/steps/kubebench.py
vessel/steps/register.py
vessel/steps/update.py
vessel/steps/vault.py
sourcesense_vessel-1.3.8.dist-info/METADATA
sourcesense_vessel-1.3.8.dist-info/WHEEL
sourcesense_vessel-1.3.8.dist-info/top_level.txt
sourcesense_vessel-1.3.8.dist-info/RECORD
