Metadata-Version: 2.1
Name: sourcesense-vessel
Version: 1.3.8
Summary: Vessel Cli Tool
Home-page: https://sourcesense.com
Author: Sourcesense spa
Author-email: open@sourcesense.com
License: all rights reserved
Platform: UNKNOWN
Classifier: Development Status :: 2 - Pre-Alpha
Classifier: License :: Other/Proprietary License
Classifier: Intended Audience :: System Administrators
Classifier: Programming Language :: Python :: 3
Requires-Python: >=3.6
Requires-Dist: click
Requires-Dist: pyfiglet
Requires-Dist: cryptography
Requires-Dist: requests
Requires-Dist: hvac
Requires-Dist: kubernetes
Requires-Dist: jinja2
